shell_as_service/__init__.py
shell_as_service/_test.py
shell_as_service/client.py
shell_as_service/server.py
shell_as_service-0.1.11.dist-info/METADATA
shell_as_service-0.1.11.dist-info/WHEEL
shell_as_service-0.1.11.dist-info/entry_points.txt
shell_as_service-0.1.11.dist-info/top_level.txt
shell_as_service-0.1.11.dist-info/RECORD
